zrep/__init__.py
zrep/zrep.py
zrep-0.1.1.dist-info/METADATA
zrep-0.1.1.dist-info/WHEEL
zrep-0.1.1.dist-info/entry_points.txt
zrep-0.1.1.dist-info/RECORD
