Metadata-Version: 2.1
Name: zrep
Version: 0.1.1
Summary: replace tool
Author: bigzhu
Author-email: vermiliondun@gmail.com
Requires-Python: >=3.10,<4.0
Classifier: Programming Language :: Python :: 3
Classifier: Programming Language :: Python :: 3.10
Classifier: Programming Language :: Python :: 3.11
Classifier: Programming Language :: Python :: 3.12
Requires-Dist: python-magic (>=0.4.27,<0.5.0)
